abnumber/__init__.py
abnumber/__version__.py
abnumber/alignment.py
abnumber/chain.py
abnumber/common.py
abnumber/exceptions.py
abnumber/future.py
abnumber/germlines.py
abnumber/position.py
abnumber-0.4.4.dist-info/licenses/LICENSE
abnumber-0.4.4.dist-info/METADATA
abnumber-0.4.4.dist-info/WHEEL
abnumber-0.4.4.dist-info/top_level.txt
abnumber-0.4.4.dist-info/RECORD
