Metadata-Version: 2.4
Name: abnumber
Version: 0.4.4
Summary: AbNumber - Antibody numbering using ANARCI
Home-page: https://github.com/prihoda/abnumber
Author: David Prihoda
Author-email: david.prihoda@gmail.com
License: MIT
Keywords: antibody numbering,immunoglobulin,ab,ANARCI,chain,imgt,chothia
Requires-Python: >=3.6
License-File: LICENSE
Requires-Dist: biopython
Requires-Dist: pandas
Requires-Dist: anarcii
Dynamic: author
Dynamic: author-email
Dynamic: description
Dynamic: description-content-type
Dynamic: home-page
Dynamic: keywords
Dynamic: license
Dynamic: license-file
Dynamic: requires-dist
Dynamic: requires-python
Dynamic: summary
